chaindl/__init__.py
chaindl/download.py
chaindl/scraper/__init__.py
chaindl/scraper/bitbo.py
chaindl/scraper/bitcoinmagazinepro.py
chaindl/scraper/blockchain.py
chaindl/scraper/chainexposed.py
chaindl/scraper/checkonchain.py
chaindl/scraper/cryptoquant.py
chaindl/scraper/dune.py
chaindl/scraper/glassnode.py
chaindl/scraper/theblock.py
chaindl/scraper/utils.py
chaindl/scraper/woocharts.py
chaindl-0.1.1.dist-info/licenses/LICENSE
chaindl-0.1.1.dist-info/METADATA
chaindl-0.1.1.dist-info/WHEEL
chaindl-0.1.1.dist-info/top_level.txt
chaindl-0.1.1.dist-info/RECORD
