Metadata-Version: 2.4
Name: chaindl
Version: 0.1.1
Summary: Download crypto on-chain data with a single line of code 
Author-email: Dhruvan Gnanadhandayuthapani <dhruvan2006@gmail.com>
License-Expression: MIT
Project-URL: Homepage, https://github.com/dhruvan2006/chaindl
Project-URL: Documentation, https://chaindl.readthedocs.io/
Project-URL: PyPI, https://pypi.org/project/chaindl/
Project-URL: Issues, https://github.com/dhruvan2006/chaindl/issues
Classifier: Programming Language :: Python :: 3
Classifier: Development Status :: 5 - Production/Stable
Classifier: Operating System :: OS Independent
Requires-Python: >=3.8
License-File: LICENSE
Requires-Dist: requests
Requires-Dist: pandas
Requires-Dist: beautifulsoup4
Requires-Dist: seleniumbase
Requires-Dist: selenium
Requires-Dist: selenium-wire
Requires-Dist: blinker==1.7.0
Requires-Dist: cloudscraper
Dynamic: license-file
